{
    "input_path": null,
    "page_index": null,
    "model_settings": {
        "use_doc_preprocessor": true,
        "use_textline_orientation": true
    },
    "doc_preprocessor_res": {
        "input_path": null,
        "page_index": null,
        "model_settings": {
            "use_doc_orientation_classify": true,
            "use_doc_unwarping": true
        },
        "angle": 0
    },
    "dt_polys": [
        [
            [
                4,
                2
            ],
            [
                47,
                2
            ],
            [
                47,
                52
            ],
            [
                4,
                52
            ]
        ],
        [
            [
                681,
                23
            ],
            [
                859,
                26
            ],
            [
                858,
                58
            ],
            [
                681,
                55
            ]
        ],
        [
            [
                855,
                27
            ],
            [
                956,
                29
            ],
            [
                956,
                59
            ],
            [
                854,
                57
            ]
        ],
        [
            [
                951,
                30
            ],
            [
                1017,
                30
            ],
            [
                1017,
                60
            ],
            [
                951,
                60
            ]
        ],
        [
            [
                1014,
                28
            ],
            [
                1399,
                31
            ],
            [
                1399,
                66
            ],
            [
                1013,
                63
            ]
        ],
        [
            [
                1392,
                33
            ],
            [
                1457,
                33
            ],
            [
                1457,
                63
            ],
            [
                1392,
                63
            ]
        ],
        [
            [
                1454,
                32
            ],
            [
                1597,
                31
            ],
            [
                1597,
                61
            ],
            [
                1454,
                62
            ]
        ],
        [
            [
                1580,
                30
            ],
            [
                1753,
                27
            ],
            [
                1754,
                60
            ],
            [
                1580,
                63
            ]
        ],
        [
            [
                610,
                61
            ],
            [
                748,
                64
            ],
            [
                748,
                94
            ],
            [
                609,
                91
            ]
        ],
        [
            [
                736,
                63
            ],
            [
                919,
                65
            ],
            [
                919,
                96
            ],
            [
                736,
                94
            ]
        ],
        [
            [
                917,
                68
            ],
            [
                952,
                68
            ],
            [
                952,
                95
            ],
            [
                917,
                95
            ]
        ],
        [
            [
                949,
                66
            ],
            [
                1104,
                66
            ],
            [
                1104,
                98
            ],
            [
                949,
                98
            ]
        ],
        [
            [
                1098,
                66
            ],
            [
                1249,
                68
            ],
            [
                1249,
                100
            ],
            [
                1098,
                98
            ]
        ],
        [
            [
                1249,
                72
            ],
            [
                1288,
                72
            ],
            [
                1288,
                98
            ],
            [
                1249,
                98
            ]
        ],
        [
            [
                1281,
                71
            ],
            [
                1327,
                71
            ],
            [
                1327,
                100
            ],
            [
                1281,
                100
            ]
        ],
        [
            [
                1325,
                71
            ],
            [
                1425,
                71
            ],
            [
                1425,
                100
            ],
            [
                1325,
                100
            ]
        ],
        [
            [
                1423,
                72
            ],
            [
                1468,
                72
            ],
            [
                1468,
                100
            ],
            [
                1423,
                100
            ]
        ],
        [
            [
                1466,
                69
            ],
            [
                1529,
                69
            ],
            [
                1529,
                100
            ],
            [
                1466,
                100
            ]
        ],
        [
            [
                1529,
                69
            ],
            [
                1660,
                69
            ],
            [
                1660,
                98
            ],
            [
                1529,
                98
            ]
        ],
        [
            [
                1661,
                67
            ],
            [
                1696,
                67
            ],
            [
                1696,
                98
            ],
            [
                1661,
                98
            ]
        ],
        [
            [
                1691,
                65
            ],
            [
                1828,
                65
            ],
            [
                1828,
                100
            ],
            [
                1691,
                100
            ]
        ],
        [
            [
                403,
                109
            ],
            [
                597,
                112
            ],
            [
                596,
                141
            ],
            [
                403,
                138
            ]
        ],
        [
            [
                869,
                107
            ],
            [
                1009,
                107
            ],
            [
                1009,
                136
            ],
            [
                869,
                136
            ]
        ],
        [
            [
                993,
                109
            ],
            [
                1178,
                111
            ],
            [
                1178,
                137
            ],
            [
                993,
                135
            ]
        ],
        [
            [
                1418,
                114
            ],
            [
                1509,
                114
            ],
            [
                1509,
                137
            ],
            [
                1418,
                137
            ]
        ],
        [
            [
                1510,
                113
            ],
            [
                1551,
                113
            ],
            [
                1551,
                138
            ],
            [
                1510,
                138
            ]
        ],
        [
            [
                1552,
                112
            ],
            [
                1647,
                112
            ],
            [
                1647,
                138
            ],
            [
                1552,
                138
            ]
        ],
        [
            [
                1648,
                111
            ],
            [
                1719,
                111
            ],
            [
                1719,
                138
            ],
            [
                1648,
                138
            ]
        ],
        [
            [
                1717,
                110
            ],
            [
                1778,
                110
            ],
            [
                1778,
                138
            ],
            [
                1717,
                138
            ]
        ],
        [
            [
                1759,
                105
            ],
            [
                2346,
                104
            ],
            [
                2346,
                139
            ],
            [
                1760,
                140
            ]
        ],
        [
            [
                21,
                133
            ],
            [
                164,
                136
            ],
            [
                163,
                165
            ],
            [
                20,
                162
            ]
        ],
        [
            [
                244,
                135
            ],
            [
                310,
                138
            ],
            [
                308,
                168
            ],
            [
                243,
                165
            ]
        ],
        [
            [
                450,
                140
            ],
            [
                550,
                140
            ],
            [
                550,
                169
            ],
            [
                450,
                169
            ]
        ],
        [
            [
                682,
                141
            ],
            [
                749,
                141
            ],
            [
                749,
                167
            ],
            [
                682,
                167
            ]
        ],
        [
            [
                747,
                142
            ],
            [
                816,
                142
            ],
            [
                816,
                168
            ],
            [
                747,
                168
            ]
        ],
        [
            [
                824,
                143
            ],
            [
                893,
                145
            ],
            [
                892,
                169
            ],
            [
                823,
                167
            ]
        ],
        [
            [
                891,
                144
            ],
            [
                978,
                144
            ],
            [
                978,
                167
            ],
            [
                891,
                167
            ]
        ],
        [
            [
                1071,
                139
            ],
            [
                1138,
                141
            ],
            [
                1137,
                168
            ],
            [
                1070,
                165
            ]
        ],
        [
            [
                1137,
                140
            ],
            [
                1364,
                144
            ],
            [
                1363,
                172
            ],
            [
                1137,
                168
            ]
        ],
        [
            [
                1417,
                143
            ],
            [
                1468,
                143
            ],
            [
                1468,
                163
            ],
            [
                1417,
                163
            ]
        ],
        [
            [
                1468,
                144
            ],
            [
                1499,
                144
            ],
            [
                1499,
                162
            ],
            [
                1468,
                162
            ]
        ],
        [
            [
                1494,
                142
            ],
            [
                1615,
                142
            ],
            [
                1615,
                164
            ],
            [
                1494,
                164
            ]
        ],
        [
            [
                1615,
                140
            ],
            [
                1674,
                140
            ],
            [
                1674,
                163
            ],
            [
                1615,
                163
            ]
        ],
        [
            [
                1670,
                138
            ],
            [
                2171,
                134
            ],
            [
                2171,
                162
            ],
            [
                1670,
                166
            ]
        ],
        [
            [
                8,
                160
            ],
            [
                180,
                162
            ],
            [
                180,
                188
            ],
            [
                8,
                186
            ]
        ],
        [
            [
                249,
                160
            ],
            [
                307,
                163
            ],
            [
                305,
                191
            ],
            [
                248,
                188
            ]
        ],
        [
            [
                381,
                163
            ],
            [
                620,
                167
            ],
            [
                619,
                196
            ],
            [
                380,
                192
            ]
        ],
        [
            [
                648,
                178
            ],
            [
                754,
                180
            ],
            [
                754,
                213
            ],
            [
                648,
                211
            ]
        ],
        [
            [
                786,
                180
            ],
            [
                867,
                180
            ],
            [
                867,
                207
            ],
            [
                786,
                207
            ]
        ],
        [
            [
                918,
                179
            ],
            [
                984,
                182
            ],
            [
                982,
                210
            ],
            [
                917,
                207
            ]
        ],
        [
            [
                1039,
                182
            ],
            [
                1139,
                182
            ],
            [
                1139,
                212
            ],
            [
                1039,
                212
            ]
        ],
        [
            [
                1172,
                182
            ],
            [
                1254,
                182
            ],
            [
                1254,
                209
            ],
            [
                1172,
                209
            ]
        ],
        [
            [
                1305,
                183
            ],
            [
                1371,
                183
            ],
            [
                1371,
                210
            ],
            [
                1305,
                210
            ]
        ],
        [
            [
                1416,
                184
            ],
            [
                1555,
                184
            ],
            [
                1555,
                209
            ],
            [
                1416,
                209
            ]
        ],
        [
            [
                1555,
                183
            ],
            [
                1667,
                183
            ],
            [
                1667,
                209
            ],
            [
                1555,
                209
            ]
        ],
        [
            [
                1668,
                183
            ],
            [
                1748,
                183
            ],
            [
                1748,
                209
            ],
            [
                1668,
                209
            ]
        ],
        [
            [
                1748,
                183
            ],
            [
                1801,
                183
            ],
            [
                1801,
                207
            ],
            [
                1748,
                207
            ]
        ],
        [
            [
                1790,
                179
            ],
            [
                2208,
                178
            ],
            [
                2208,
                209
            ],
            [
                1790,
                210
            ]
        ],
        [
            [
                659,
                208
            ],
            [
                744,
                208
            ],
            [
                744,
                238
            ],
            [
                659,
                238
            ]
        ],
        [
            [
                791,
                209
            ],
            [
                862,
                209
            ],
            [
                862,
                235
            ],
            [
                791,
                235
            ]
        ],
        [
            [
                924,
                210
            ],
            [
                978,
                210
            ],
            [
                978,
                234
            ],
            [
                924,
                234
            ]
        ],
        [
            [
                1048,
                210
            ],
            [
                1130,
                210
            ],
            [
                1130,
                237
            ],
            [
                1048,
                237
            ]
        ],
        [
            [
                1177,
                207
            ],
            [
                1249,
                210
            ],
            [
                1248,
                237
            ],
            [
                1176,
                234
            ]
        ],
        [
            [
                1312,
                211
            ],
            [
                1366,
                211
            ],
            [
                1366,
                235
            ],
            [
                1312,
                235
            ]
        ],
        [
            [
                1416,
                212
            ],
            [
                1509,
                212
            ],
            [
                1509,
                234
            ],
            [
                1416,
                234
            ]
        ],
        [
            [
                1506,
                214
            ],
            [
                1627,
                214
            ],
            [
                1627,
                233
            ],
            [
                1506,
                233
            ]
        ],
        [
            [
                1627,
                212
            ],
            [
                1690,
                212
            ],
            [
                1690,
                235
            ],
            [
                1627,
                235
            ]
        ],
        [
            [
                1681,
                209
            ],
            [
                2062,
                207
            ],
            [
                2062,
                235
            ],
            [
                1681,
                237
            ]
        ],
        [
            [
                1687,
                243
            ],
            [
                1754,
                243
            ],
            [
                1754,
                273
            ],
            [
                1687,
                273
            ]
        ],
        [
            [
                435,
                253
            ],
            [
                563,
                253
            ],
            [
                563,
                282
            ],
            [
                435,
                282
            ]
        ],
        [
            [
                78,
                266
            ],
            [
                121,
                266
            ],
            [
                121,
                295
            ],
            [
                78,
                295
            ]
        ],
        [
            [
                197,
                264
            ],
            [
                353,
                268
            ],
            [
                352,
                297
            ],
            [
                197,
                293
            ]
        ],
        [
            [
                929,
                272
            ],
            [
                966,
                272
            ],
            [
                966,
                298
            ],
            [
                929,
                298
            ]
        ],
        [
            [
                1411,
                273
            ],
            [
                1680,
                273
            ],
            [
                1680,
                298
            ],
            [
                1411,
                298
            ]
        ],
        [
            [
                1690,
                297
            ],
            [
                1749,
                297
            ],
            [
                1749,
                325
            ],
            [
                1690,
                325
            ]
        ],
        [
            [
                432,
                336
            ],
            [
                563,
                339
            ],
            [
                562,
                368
            ],
            [
                432,
                365
            ]
        ],
        [
            [
                1677,
                332
            ],
            [
                1745,
                332
            ],
            [
                1745,
                362
            ],
            [
                1677,
                362
            ]
        ],
        [
            [
                80,
                352
            ],
            [
                123,
                352
            ],
            [
                123,
                381
            ],
            [
                80,
                381
            ]
        ],
        [
            [
                196,
                349
            ],
            [
                353,
                352
            ],
            [
                352,
                382
            ],
            [
                196,
                379
            ]
        ],
        [
            [
                907,
                356
            ],
            [
                987,
                356
            ],
            [
                987,
                383
            ],
            [
                907,
                383
            ]
        ],
        [
            [
                1405,
                352
            ],
            [
                1681,
                355
            ],
            [
                1681,
                384
            ],
            [
                1405,
                381
            ]
        ],
        [
            [
                1692,
                358
            ],
            [
                1726,
                358
            ],
            [
                1726,
                386
            ],
            [
                1692,
                386
            ]
        ],
        [
            [
                1679,
                387
            ],
            [
                1738,
                387
            ],
            [
                1738,
                411
            ],
            [
                1679,
                411
            ]
        ],
        [
            [
                1596,
                406
            ],
            [
                1664,
                406
            ],
            [
                1664,
                435
            ],
            [
                1596,
                435
            ]
        ],
        [
            [
                433,
                420
            ],
            [
                562,
                420
            ],
            [
                562,
                449
            ],
            [
                433,
                449
            ]
        ],
        [
            [
                81,
                436
            ],
            [
                125,
                436
            ],
            [
                125,
                465
            ],
            [
                81,
                465
            ]
        ],
        [
            [
                198,
                435
            ],
            [
                354,
                435
            ],
            [
                354,
                464
            ],
            [
                198,
                464
            ]
        ],
        [
            [
                676,
                436
            ],
            [
                717,
                436
            ],
            [
                717,
                465
            ],
            [
                676,
                465
            ]
        ],
        [
            [
                906,
                438
            ],
            [
                987,
                438
            ],
            [
                987,
                465
            ],
            [
                906,
                465
            ]
        ],
        [
            [
                1410,
                439
            ],
            [
                1592,
                439
            ],
            [
                1592,
                465
            ],
            [
                1410,
                465
            ]
        ],
        [
            [
                463,
                458
            ],
            [
                530,
                458
            ],
            [
                530,
                485
            ],
            [
                463,
                485
            ]
        ],
        [
            [
                1598,
                458
            ],
            [
                1660,
                455
            ],
            [
                1662,
                486
            ],
            [
                1600,
                489
            ]
        ],
        [
            [
                1276,
                1271
            ],
            [
                1284,
                1269
            ],
            [
                1287,
                1281
            ],
            [
                1279,
                1283
            ]
        ]
    ],
    "text_det_params": {
        "limit_side_len": 64,
        "limit_type": "min",
        "thresh": 0.25,
        "max_side_limit": 4000,
        "box_thresh": 0.3,
        "unclip_ratio": 1.8
    },
    "text_type": "general",
    "textline_orientation_angles": [
        0,
        0,
        0,
        0,
        0,
        0,
        0,
        0,
        0,
        0,
        0,
        0,
        0,
        0,
        0,
        0,
        0,
        0,
        0,
        0,
        0,
        0,
        0,
        0,
        0,
        0,
        0,
        0,
        0,
        0,
        0,
        0,
        0,
        0,
        0,
        0,
        0,
        0,
        0,
        0,
        0,
        0,
        0,
        0,
        0,
        0,
        0,
        0,
        0,
        0,
        0,
        0,
        0,
        0,
        0,
        0,
        0,
        0,
        0,
        0,
        0,
        0,
        0,
        0,
        0,
        0,
        0,
        0,
        0,
        0,
        0,
        0,
        0,
        0,
        0,
        0,
        0,
        0,
        0,
        0,
        0,
        0,
        0,
        0,
        0,
        0,
        0,
        0,
        0,
        0,
        0,
        0,
        1
    ],
    "text_rec_score_thresh": 0.0,
    "rec_texts": [
        "7",
        "Successive",
        "status",
        "and",
        "minor/major maintenance",
        "and",
        "overhaul",
        "I operations",
        "Positions",
        "successives",
        "et",
        "opérations",
        "d'entretien",
        "et",
        "de",
        "remise",
        "en",
        "état",
        "mineures",
        "et",
        "majeures",
        "Aircraft Version",
        "Operations",
        "s / Fonctionnement",
        "Reason",
        "for",
        "transfer",
        "(code",
        "ands",
        "symptoms) - Accomplished work - Replaced part",
        "Contractor",
        "Date",
        "and S/N",
        "Unit /",
        "Unité :",
        "Hours",
        "/ Heures",
        "Unit I",
        "Unité : Cycles / Cycles",
        "Motif",
        "du",
        "mouvement",
        "(code",
        "symptômes) - Travaux effectués - Pièces changées",
        "Unité ou société",
        "Date",
        "Version et No d'appareil",
        "Support",
        "Partiel",
        "Total",
        "Support",
        "Partiel",
        "Total",
        "Successive",
        "locations",
        "before",
        "A/C",
        "delivery - See front page of table 5",
        "Support",
        "Partial",
        "Total",
        "Support",
        "Partial",
        "Total",
        "Positions",
        "successives",
        "avant",
        " livraison appareil - Voir recto tableau 5",
        "F0210",
        "H 160 -B",
        "AH",
        "12/06/2023",
        "OH",
        "First installation",
        "a ab",
        "H 160 -B",
        "F0210",
        "AH",
        "12/12/2023",
        "04H26",
        "AH final operation",
        "e",
        "aab",
        "F0210",
        "H 160 -B",
        "AH",
        "16/01/2024",
        "OH",
        "04H26",
        "Installation",
        "1054",
        "aab",
        "□"
    ],
    "rec_scores": [
        0.9999054670333862,
        0.9999099969863892,
        0.9999215602874756,
        0.9999747276306152,
        0.9992525577545166,
        0.9999842643737793,
        0.9998628497123718,
        0.9487864971160889,
        0.999968409538269,
        0.9995556473731995,
        0.9999696612358093,
        0.999971866607666,
        0.9997951984405518,
        0.9999549984931946,
        0.9999846816062927,
        0.9997448325157166,
        0.9999792575836182,
        0.9473282694816589,
        0.9997338056564331,
        0.9999806880950928,
        0.9998654127120972,
        0.9816689491271973,
        0.9999195337295532,
        0.9636718034744263,
        0.9999439716339111,
        0.9998886585235596,
        0.9998417496681213,
        0.9997965097427368,
        0.9241162538528442,
        0.9993782639503479,
        0.9998941421508789,
        0.9999125003814697,
        0.9977266192436218,
        0.9512808918952942,
        0.9995089173316956,
        0.9999063611030579,
        0.9898061752319336,
        0.908196747303009,
        0.9930974841117859,
        0.999717116355896,
        0.9999756217002869,
        0.9998955130577087,
        0.9994640350341797,
        0.9941777586936951,
        0.9993979930877686,
        0.9995713233947754,
        0.9990010857582092,
        0.9998950958251953,
        0.9999547004699707,
        0.9999581575393677,
        0.9999265074729919,
        0.9999285936355591,
        0.9999703168869019,
        0.9998738169670105,
        0.9997068047523499,
        0.9998524785041809,
        0.9609225392341614,
        0.9949372410774231,
        0.9998682737350464,
        0.9999685287475586,
        0.9999817609786987,
        0.9999294877052307,
        0.9998551607131958,
        0.9999735951423645,
        0.9998593926429749,
        0.9913881421089172,
        0.9998558163642883,
        0.9889301061630249,
        0.9980149269104004,
        0.9812164306640625,
        0.9998781681060791,
        0.9987983703613281,
        0.899420976638794,
        0.9808856248855591,
        0.9101983308792114,
        0.9865168333053589,
        0.9979556798934937,
        0.9998716115951538,
        0.9986666440963745,
        0.9999000430107117,
        0.9991276860237122,
        0.6111555099487305,
        0.9984263777732849,
        0.9832237362861633,
        0.9640147089958191,
        0.9998902678489685,
        0.9981986880302429,
        0.9617214798927307,
        0.9999343156814575,
        0.9999136328697205,
        0.9999632835388184,
        0.9887414574623108,
        0.6458024382591248
    ],
    "rec_polys": [
        [
            [
                4,
                2
            ],
            [
                47,
                2
            ],
            [
                47,
                52
            ],
            [
                4,
                52
            ]
        ],
        [
            [
                681,
                23
            ],
            [
                859,
                26
            ],
            [
                858,
                58
            ],
            [
                681,
                55
            ]
        ],
        [
            [
                855,
                27
            ],
            [
                956,
                29
            ],
            [
                956,
                59
            ],
            [
                854,
                57
            ]
        ],
        [
            [
                951,
                30
            ],
            [
                1017,
                30
            ],
            [
                1017,
                60
            ],
            [
                951,
                60
            ]
        ],
        [
            [
                1014,
                28
            ],
            [
                1399,
                31
            ],
            [
                1399,
                66
            ],
            [
                1013,
                63
            ]
        ],
        [
            [
                1392,
                33
            ],
            [
                1457,
                33
            ],
            [
                1457,
                63
            ],
            [
                1392,
                63
            ]
        ],
        [
            [
                1454,
                32
            ],
            [
                1597,
                31
            ],
            [
                1597,
                61
            ],
            [
                1454,
                62
            ]
        ],
        [
            [
                1580,
                30
            ],
            [
                1753,
                27
            ],
            [
                1754,
                60
            ],
            [
                1580,
                63
            ]
        ],
        [
            [
                610,
                61
            ],
            [
                748,
                64
            ],
            [
                748,
                94
            ],
            [
                609,
                91
            ]
        ],
        [
            [
                736,
                63
            ],
            [
                919,
                65
            ],
            [
                919,
                96
            ],
            [
                736,
                94
            ]
        ],
        [
            [
                917,
                68
            ],
            [
                952,
                68
            ],
            [
                952,
                95
            ],
            [
                917,
                95
            ]
        ],
        [
            [
                949,
                66
            ],
            [
                1104,
                66
            ],
            [
                1104,
                98
            ],
            [
                949,
                98
            ]
        ],
        [
            [
                1098,
                66
            ],
            [
                1249,
                68
            ],
            [
                1249,
                100
            ],
            [
                1098,
                98
            ]
        ],
        [
            [
                1249,
                72
            ],
            [
                1288,
                72
            ],
            [
                1288,
                98
            ],
            [
                1249,
                98
            ]
        ],
        [
            [
                1281,
                71
            ],
            [
                1327,
                71
            ],
            [
                1327,
                100
            ],
            [
                1281,
                100
            ]
        ],
        [
            [
                1325,
                71
            ],
            [
                1425,
                71
            ],
            [
                1425,
                100
            ],
            [
                1325,
                100
            ]
        ],
        [
            [
                1423,
                72
            ],
            [
                1468,
                72
            ],
            [
                1468,
                100
            ],
            [
                1423,
                100
            ]
        ],
        [
            [
                1466,
                69
            ],
            [
                1529,
                69
            ],
            [
                1529,
                100
            ],
            [
                1466,
                100
            ]
        ],
        [
            [
                1529,
                69
            ],
            [
                1660,
                69
            ],
            [
                1660,
                98
            ],
            [
                1529,
                98
            ]
        ],
        [
            [
                1661,
                67
            ],
            [
                1696,
                67
            ],
            [
                1696,
                98
            ],
            [
                1661,
                98
            ]
        ],
        [
            [
                1691,
                65
            ],
            [
                1828,
                65
            ],
            [
                1828,
                100
            ],
            [
                1691,
                100
            ]
        ],
        [
            [
                403,
                109
            ],
            [
                597,
                112
            ],
            [
                596,
                141
            ],
            [
                403,
                138
            ]
        ],
        [
            [
                869,
                107
            ],
            [
                1009,
                107
            ],
            [
                1009,
                136
            ],
            [
                869,
                136
            ]
        ],
        [
            [
                993,
                109
            ],
            [
                1178,
                111
            ],
            [
                1178,
                137
            ],
            [
                993,
                135
            ]
        ],
        [
            [
                1418,
                114
            ],
            [
                1509,
                114
            ],
            [
                1509,
                137
            ],
            [
                1418,
                137
            ]
        ],
        [
            [
                1510,
                113
            ],
            [
                1551,
                113
            ],
            [
                1551,
                138
            ],
            [
                1510,
                138
            ]
        ],
        [
            [
                1552,
                112
            ],
            [
                1647,
                112
            ],
            [
                1647,
                138
            ],
            [
                1552,
                138
            ]
        ],
        [
            [
                1648,
                111
            ],
            [
                1719,
                111
            ],
            [
                1719,
                138
            ],
            [
                1648,
                138
            ]
        ],
        [
            [
                1717,
                110
            ],
            [
                1778,
                110
            ],
            [
                1778,
                138
            ],
            [
                1717,
                138
            ]
        ],
        [
            [
                1759,
                105
            ],
            [
                2346,
                104
            ],
            [
                2346,
                139
            ],
            [
                1760,
                140
            ]
        ],
        [
            [
                21,
                133
            ],
            [
                164,
                136
            ],
            [
                163,
                165
            ],
            [
                20,
                162
            ]
        ],
        [
            [
                244,
                135
            ],
            [
                310,
                138
            ],
            [
                308,
                168
            ],
            [
                243,
                165
            ]
        ],
        [
            [
                450,
                140
            ],
            [
                550,
                140
            ],
            [
                550,
                169
            ],
            [
                450,
                169
            ]
        ],
        [
            [
                682,
                141
            ],
            [
                749,
                141
            ],
            [
                749,
                167
            ],
            [
                682,
                167
            ]
        ],
        [
            [
                747,
                142
            ],
            [
                816,
                142
            ],
            [
                816,
                168
            ],
            [
                747,
                168
            ]
        ],
        [
            [
                824,
                143
            ],
            [
                893,
                145
            ],
            [
                892,
                169
            ],
            [
                823,
                167
            ]
        ],
        [
            [
                891,
                144
            ],
            [
                978,
                144
            ],
            [
                978,
                167
            ],
            [
                891,
                167
            ]
        ],
        [
            [
                1071,
                139
            ],
            [
                1138,
                141
            ],
            [
                1137,
                168
            ],
            [
                1070,
                165
            ]
        ],
        [
            [
                1137,
                140
            ],
            [
                1364,
                144
            ],
            [
                1363,
                172
            ],
            [
                1137,
                168
            ]
        ],
        [
            [
                1417,
                143
            ],
            [
                1468,
                143
            ],
            [
                1468,
                163
            ],
            [
                1417,
                163
            ]
        ],
        [
            [
                1468,
                144
            ],
            [
                1499,
                144
            ],
            [
                1499,
                162
            ],
            [
                1468,
                162
            ]
        ],
        [
            [
                1494,
                142
            ],
            [
                1615,
                142
            ],
            [
                1615,
                164
            ],
            [
                1494,
                164
            ]
        ],
        [
            [
                1615,
                140
            ],
            [
                1674,
                140
            ],
            [
                1674,
                163
            ],
            [
                1615,
                163
            ]
        ],
        [
            [
                1670,
                138
            ],
            [
                2171,
                134
            ],
            [
                2171,
                162
            ],
            [
                1670,
                166
            ]
        ],
        [
            [
                8,
                160
            ],
            [
                180,
                162
            ],
            [
                180,
                188
            ],
            [
                8,
                186
            ]
        ],
        [
            [
                249,
                160
            ],
            [
                307,
                163
            ],
            [
                305,
                191
            ],
            [
                248,
                188
            ]
        ],
        [
            [
                381,
                163
            ],
            [
                620,
                167
            ],
            [
                619,
                196
            ],
            [
                380,
                192
            ]
        ],
        [
            [
                648,
                178
            ],
            [
                754,
                180
            ],
            [
                754,
                213
            ],
            [
                648,
                211
            ]
        ],
        [
            [
                786,
                180
            ],
            [
                867,
                180
            ],
            [
                867,
                207
            ],
            [
                786,
                207
            ]
        ],
        [
            [
                918,
                179
            ],
            [
                984,
                182
            ],
            [
                982,
                210
            ],
            [
                917,
                207
            ]
        ],
        [
            [
                1039,
                182
            ],
            [
                1139,
                182
            ],
            [
                1139,
                212
            ],
            [
                1039,
                212
            ]
        ],
        [
            [
                1172,
                182
            ],
            [
                1254,
                182
            ],
            [
                1254,
                209
            ],
            [
                1172,
                209
            ]
        ],
        [
            [
                1305,
                183
            ],
            [
                1371,
                183
            ],
            [
                1371,
                210
            ],
            [
                1305,
                210
            ]
        ],
        [
            [
                1416,
                184
            ],
            [
                1555,
                184
            ],
            [
                1555,
                209
            ],
            [
                1416,
                209
            ]
        ],
        [
            [
                1555,
                183
            ],
            [
                1667,
                183
            ],
            [
                1667,
                209
            ],
            [
                1555,
                209
            ]
        ],
        [
            [
                1668,
                183
            ],
            [
                1748,
                183
            ],
            [
                1748,
                209
            ],
            [
                1668,
                209
            ]
        ],
        [
            [
                1748,
                183
            ],
            [
                1801,
                183
            ],
            [
                1801,
                207
            ],
            [
                1748,
                207
            ]
        ],
        [
            [
                1790,
                179
            ],
            [
                2208,
                178
            ],
            [
                2208,
                209
            ],
            [
                1790,
                210
            ]
        ],
        [
            [
                659,
                208
            ],
            [
                744,
                208
            ],
            [
                744,
                238
            ],
            [
                659,
                238
            ]
        ],
        [
            [
                791,
                209
            ],
            [
                862,
                209
            ],
            [
                862,
                235
            ],
            [
                791,
                235
            ]
        ],
        [
            [
                924,
                210
            ],
            [
                978,
                210
            ],
            [
                978,
                234
            ],
            [
                924,
                234
            ]
        ],
        [
            [
                1048,
                210
            ],
            [
                1130,
                210
            ],
            [
                1130,
                237
            ],
            [
                1048,
                237
            ]
        ],
        [
            [
                1177,
                207
            ],
            [
                1249,
                210
            ],
            [
                1248,
                237
            ],
            [
                1176,
                234
            ]
        ],
        [
            [
                1312,
                211
            ],
            [
                1366,
                211
            ],
            [
                1366,
                235
            ],
            [
                1312,
                235
            ]
        ],
        [
            [
                1416,
                212
            ],
            [
                1509,
                212
            ],
            [
                1509,
                234
            ],
            [
                1416,
                234
            ]
        ],
        [
            [
                1506,
                214
            ],
            [
                1627,
                214
            ],
            [
                1627,
                233
            ],
            [
                1506,
                233
            ]
        ],
        [
            [
                1627,
                212
            ],
            [
                1690,
                212
            ],
            [
                1690,
                235
            ],
            [
                1627,
                235
            ]
        ],
        [
            [
                1681,
                209
            ],
            [
                2062,
                207
            ],
            [
                2062,
                235
            ],
            [
                1681,
                237
            ]
        ],
        [
            [
                1687,
                243
            ],
            [
                1754,
                243
            ],
            [
                1754,
                273
            ],
            [
                1687,
                273
            ]
        ],
        [
            [
                435,
                253
            ],
            [
                563,
                253
            ],
            [
                563,
                282
            ],
            [
                435,
                282
            ]
        ],
        [
            [
                78,
                266
            ],
            [
                121,
                266
            ],
            [
                121,
                295
            ],
            [
                78,
                295
            ]
        ],
        [
            [
                197,
                264
            ],
            [
                353,
                268
            ],
            [
                352,
                297
            ],
            [
                197,
                293
            ]
        ],
        [
            [
                929,
                272
            ],
            [
                966,
                272
            ],
            [
                966,
                298
            ],
            [
                929,
                298
            ]
        ],
        [
            [
                1411,
                273
            ],
            [
                1680,
                273
            ],
            [
                1680,
                298
            ],
            [
                1411,
                298
            ]
        ],
        [
            [
                1690,
                297
            ],
            [
                1749,
                297
            ],
            [
                1749,
                325
            ],
            [
                1690,
                325
            ]
        ],
        [
            [
                432,
                336
            ],
            [
                563,
                339
            ],
            [
                562,
                368
            ],
            [
                432,
                365
            ]
        ],
        [
            [
                1677,
                332
            ],
            [
                1745,
                332
            ],
            [
                1745,
                362
            ],
            [
                1677,
                362
            ]
        ],
        [
            [
                80,
                352
            ],
            [
                123,
                352
            ],
            [
                123,
                381
            ],
            [
                80,
                381
            ]
        ],
        [
            [
                196,
                349
            ],
            [
                353,
                352
            ],
            [
                352,
                382
            ],
            [
                196,
                379
            ]
        ],
        [
            [
                907,
                356
            ],
            [
                987,
                356
            ],
            [
                987,
                383
            ],
            [
                907,
                383
            ]
        ],
        [
            [
                1405,
                352
            ],
            [
                1681,
                355
            ],
            [
                1681,
                384
            ],
            [
                1405,
                381
            ]
        ],
        [
            [
                1692,
                358
            ],
            [
                1726,
                358
            ],
            [
                1726,
                386
            ],
            [
                1692,
                386
            ]
        ],
        [
            [
                1679,
                387
            ],
            [
                1738,
                387
            ],
            [
                1738,
                411
            ],
            [
                1679,
                411
            ]
        ],
        [
            [
                1596,
                406
            ],
            [
                1664,
                406
            ],
            [
                1664,
                435
            ],
            [
                1596,
                435
            ]
        ],
        [
            [
                433,
                420
            ],
            [
                562,
                420
            ],
            [
                562,
                449
            ],
            [
                433,
                449
            ]
        ],
        [
            [
                81,
                436
            ],
            [
                125,
                436
            ],
            [
                125,
                465
            ],
            [
                81,
                465
            ]
        ],
        [
            [
                198,
                435
            ],
            [
                354,
                435
            ],
            [
                354,
                464
            ],
            [
                198,
                464
            ]
        ],
        [
            [
                676,
                436
            ],
            [
                717,
                436
            ],
            [
                717,
                465
            ],
            [
                676,
                465
            ]
        ],
        [
            [
                906,
                438
            ],
            [
                987,
                438
            ],
            [
                987,
                465
            ],
            [
                906,
                465
            ]
        ],
        [
            [
                1410,
                439
            ],
            [
                1592,
                439
            ],
            [
                1592,
                465
            ],
            [
                1410,
                465
            ]
        ],
        [
            [
                463,
                458
            ],
            [
                530,
                458
            ],
            [
                530,
                485
            ],
            [
                463,
                485
            ]
        ],
        [
            [
                1598,
                458
            ],
            [
                1660,
                455
            ],
            [
                1662,
                486
            ],
            [
                1600,
                489
            ]
        ],
        [
            [
                1276,
                1271
            ],
            [
                1284,
                1269
            ],
            [
                1287,
                1281
            ],
            [
                1279,
                1283
            ]
        ]
    ],
    "rec_boxes": [
        [
            4,
            2,
            47,
            52
        ],
        [
            681,
            23,
            859,
            58
        ],
        [
            854,
            27,
            956,
            59
        ],
        [
            951,
            30,
            1017,
            60
        ],
        [
            1013,
            28,
            1399,
            66
        ],
        [
            1392,
            33,
            1457,
            63
        ],
        [
            1454,
            31,
            1597,
            62
        ],
        [
            1580,
            27,
            1754,
            63
        ],
        [
            609,
            61,
            748,
            94
        ],
        [
            736,
            63,
            919,
            96
        ],
        [
            917,
            68,
            952,
            95
        ],
        [
            949,
            66,
            1104,
            98
        ],
        [
            1098,
            66,
            1249,
            100
        ],
        [
            1249,
            72,
            1288,
            98
        ],
        [
            1281,
            71,
            1327,
            100
        ],
        [
            1325,
            71,
            1425,
            100
        ],
        [
            1423,
            72,
            1468,
            100
        ],
        [
            1466,
            69,
            1529,
            100
        ],
        [
            1529,
            69,
            1660,
            98
        ],
        [
            1661,
            67,
            1696,
            98
        ],
        [
            1691,
            65,
            1828,
            100
        ],
        [
            403,
            109,
            597,
            141
        ],
        [
            869,
            107,
            1009,
            136
        ],
        [
            993,
            109,
            1178,
            137
        ],
        [
            1418,
            114,
            1509,
            137
        ],
        [
            1510,
            113,
            1551,
            138
        ],
        [
            1552,
            112,
            1647,
            138
        ],
        [
            1648,
            111,
            1719,
            138
        ],
        [
            1717,
            110,
            1778,
            138
        ],
        [
            1759,
            104,
            2346,
            140
        ],
        [
            20,
            133,
            164,
            165
        ],
        [
            243,
            135,
            310,
            168
        ],
        [
            450,
            140,
            550,
            169
        ],
        [
            682,
            141,
            749,
            167
        ],
        [
            747,
            142,
            816,
            168
        ],
        [
            823,
            143,
            893,
            169
        ],
        [
            891,
            144,
            978,
            167
        ],
        [
            1070,
            139,
            1138,
            168
        ],
        [
            1137,
            140,
            1364,
            172
        ],
        [
            1417,
            143,
            1468,
            163
        ],
        [
            1468,
            144,
            1499,
            162
        ],
        [
            1494,
            142,
            1615,
            164
        ],
        [
            1615,
            140,
            1674,
            163
        ],
        [
            1670,
            134,
            2171,
            166
        ],
        [
            8,
            160,
            180,
            188
        ],
        [
            248,
            160,
            307,
            191
        ],
        [
            380,
            163,
            620,
            196
        ],
        [
            648,
            178,
            754,
            213
        ],
        [
            786,
            180,
            867,
            207
        ],
        [
            917,
            179,
            984,
            210
        ],
        [
            1039,
            182,
            1139,
            212
        ],
        [
            1172,
            182,
            1254,
            209
        ],
        [
            1305,
            183,
            1371,
            210
        ],
        [
            1416,
            184,
            1555,
            209
        ],
        [
            1555,
            183,
            1667,
            209
        ],
        [
            1668,
            183,
            1748,
            209
        ],
        [
            1748,
            183,
            1801,
            207
        ],
        [
            1790,
            178,
            2208,
            210
        ],
        [
            659,
            208,
            744,
            238
        ],
        [
            791,
            209,
            862,
            235
        ],
        [
            924,
            210,
            978,
            234
        ],
        [
            1048,
            210,
            1130,
            237
        ],
        [
            1176,
            207,
            1249,
            237
        ],
        [
            1312,
            211,
            1366,
            235
        ],
        [
            1416,
            212,
            1509,
            234
        ],
        [
            1506,
            214,
            1627,
            233
        ],
        [
            1627,
            212,
            1690,
            235
        ],
        [
            1681,
            207,
            2062,
            237
        ],
        [
            1687,
            243,
            1754,
            273
        ],
        [
            435,
            253,
            563,
            282
        ],
        [
            78,
            266,
            121,
            295
        ],
        [
            197,
            264,
            353,
            297
        ],
        [
            929,
            272,
            966,
            298
        ],
        [
            1411,
            273,
            1680,
            298
        ],
        [
            1690,
            297,
            1749,
            325
        ],
        [
            432,
            336,
            563,
            368
        ],
        [
            1677,
            332,
            1745,
            362
        ],
        [
            80,
            352,
            123,
            381
        ],
        [
            196,
            349,
            353,
            382
        ],
        [
            907,
            356,
            987,
            383
        ],
        [
            1405,
            352,
            1681,
            384
        ],
        [
            1692,
            358,
            1726,
            386
        ],
        [
            1679,
            387,
            1738,
            411
        ],
        [
            1596,
            406,
            1664,
            435
        ],
        [
            433,
            420,
            562,
            449
        ],
        [
            81,
            436,
            125,
            465
        ],
        [
            198,
            435,
            354,
            464
        ],
        [
            676,
            436,
            717,
            465
        ],
        [
            906,
            438,
            987,
            465
        ],
        [
            1410,
            439,
            1592,
            465
        ],
        [
            463,
            458,
            530,
            485
        ],
        [
            1598,
            455,
            1662,
            489
        ],
        [
            1276,
            1269,
            1287,
            1283
        ]
    ]
}